COPYING
MANIFEST.in
README.rst
bootstrap-buildout.py
buildout.cfg
setup.py
bob/__init__.py
bob.db.verapalm.egg-info/PKG-INFO
bob.db.verapalm.egg-info/SOURCES.txt
bob.db.verapalm.egg-info/dependency_links.txt
bob.db.verapalm.egg-info/entry_points.txt
bob.db.verapalm.egg-info/namespace_packages.txt
bob.db.verapalm.egg-info/not-zip-safe
bob.db.verapalm.egg-info/requires.txt
bob.db.verapalm.egg-info/top_level.txt
bob/db/__init__.py
bob/db/verapalm/__init__.py
bob/db/verapalm/create.py
bob/db/verapalm/db.sql3
bob/db/verapalm/driver.py
bob/db/verapalm/models.py
bob/db/verapalm/query.py
bob/db/verapalm/test.py
doc/conf.py
doc/guide.rst
doc/index.rst
doc/py_api.rst