Metadata-Version: 1.1
Name: bob.db.verapalm
Version: 2.0.0
Summary: VERA Palmvein Database Access API for Bob
Home-page: https://pypi.python.org/pypi/bob.db.verapalm
Author: Pedro Tome
Author-email: pedro.tome@idiap.ch
License: GPLv3
Keywords: fingervein recognition,bob,bob.db,VERA
Platform: UNKNOWN
Classifier: Framework :: Bob
Classifier: Development Status :: 4 - Beta
Classifier: Environment :: Console
Classifier: Intended Audience :: Developers
Classifier: Intended Audience :: Education
Classifier: Intended Audience :: Science/Research
Classifier: License :: OSI Approved :: GNU General Public License v3 (GPLv3)
Classifier: Natural Language :: English
Classifier: Programming Language :: Python
Classifier: Programming Language :: Python :: 3
Classifier: Topic :: Scientific/Engineering :: Artificial Intelligence
Classifier: Topic :: Database :: Front-Ends
